LICENSE.txt
MANIFEST.in
README.rst
pyproject.toml
setup.py
tutor_android.egg-info/PKG-INFO
tutor_android.egg-info/SOURCES.txt
tutor_android.egg-info/dependency_links.txt
tutor_android.egg-info/entry_points.txt
tutor_android.egg-info/requires.txt
tutor_android.egg-info/top_level.txt
tutorandroid/__about__.py
tutorandroid/__init__.py
tutorandroid/plugin.py
tutorandroid/patches/.gitignore
tutorandroid/patches/caddyfile
tutorandroid/patches/k8s-deployments
tutorandroid/patches/k8s-services
tutorandroid/patches/local-docker-compose-dev-services
tutorandroid/patches/local-docker-compose-services
tutorandroid/templates/android/build/.gitignore
tutorandroid/templates/android/build/Dockerfile
tutorandroid/templates/android/build/config/.gitignore
tutorandroid/templates/android/build/config/edx.properties
tutorandroid/templates/android/build/config/gradle.properties
tutorandroid/templates/android/build/config/tutor.yaml
tutorandroid/templates/android/tasks/.gitignore
tutorandroid/templates/android/tasks/lms/init